[
    {
        "query": "01/03/2020",
        "site": "https://www.eldiarioweb.com",
        "start": 1,
        "active": true
    },
    {
        "query": "01/03/2020",
        "site": "https://www.diariojornada.com.ar",
        "start": 1,
        "active": true
    },
    {
        "query": "01/03/2020",
        "site": "https://www.elpatagonico.com",
        "start": 1,
        "active": true
    },
    {
        "query": "01/03/2020",
        "site": "https://www.elchubut.com.ar",
        "start": 1,
        "active": true
    },
    {
        "query": "01/03/2020",
        "site": "https://diariocronica.com.ar",
        "start": 1,
        "active": true
    },
    {
        "query": "01/03/2020",
        "site": "https://www.adnsur.com.ar",
        "start": 1,
        "active": true
    },
    {
        "query": "marzo 01",
        "site": "https://radio3cadenapatagonia.com.ar",
        "start": 1,
        "active": true
    }
]
